<?xml version="1.0" encoding="UTF-8"?>
<odoo>

<record id="res_config_settings_view_form_pos_laundry" model="ir.ui.view">
    <field name="name">res.config.settings.view.form.pos.laundry</field>
    <field name="model">res.config.settings</field>
    <field name="inherit_id" ref="base.res_config_settings_view_form"/>
    <field name="arch" type="xml">

        <xpath expr="//form" position="inside">
            <app string="Laundry POS" name="pos_laundry">
                <block title="Package Settings">
                    <setting string="Package POS Category">
                        <field name="laundry_package_category_id"/>
                    </setting>
                </block>
                <block title="Project Settings">
                    <setting string="Is Project" help="Enable this if you want to link laundry orders to projects.">
                        <field name="is_project"/>
                    </setting>
                    <setting string="Project" help="Select the project to link laundry orders to." invisible="not is_project">
                        <field name="project_id" options="{'no_create': True}"/>
                    </setting>
                </block>
            </app>
        </xpath>

    </field>
</record>
</odoo>